vkimexp/__init__.py
vkimexp/__main__.py
vkimexp/_version.py
vkimexp/auth.py
vkimexp/cli.py
vkimexp/common.py
vkimexp/core.py
vkimexp/handler.py
vkimexp/printer.py
vkimexp/writer.py
vkimexp/data/default.css
vkimexp-1.2.0.dist-info/METADATA
vkimexp-1.2.0.dist-info/WHEEL
vkimexp-1.2.0.dist-info/entry_points.txt
vkimexp-1.2.0.dist-info/licenses/LICENSE
vkimexp-1.2.0.dist-info/RECORD
