Metadata-Version: 2.1
Name: vkimexp
Version: 1.2.0
Summary: VK messages/history export
Project-URL: Homepage, https://github.com/delameter/vkimexp
Author-email: Aleksandr Shavykin <0.delameter@gmail.com>
License-Expression: MIT
License-File: LICENSE
Keywords: cli,conversation,export,message,vk
Classifier: Development Status :: 3 - Alpha
Classifier: Environment :: Console
Classifier: License :: OSI Approved :: MIT License
Classifier: Programming Language :: Python
Classifier: Programming Language :: Python :: 3
Classifier: Programming Language :: Python :: 3.12
Requires-Python: >=3.12
Requires-Dist: beautifulsoup4==4.12.2
Requires-Dist: brotli==1.1.0
Requires-Dist: browser-cookie3==0.19.1
Requires-Dist: bs4==0.0.1
Requires-Dist: certifi==2023.7.22
Requires-Dist: cffi==1.15.1
Requires-Dist: charset-normalizer==3.2.0
Requires-Dist: click==8.1.7
Requires-Dist: cryptography==41.0.3
Requires-Dist: idna==3.4
Requires-Dist: jeepney==0.8.0
Requires-Dist: lz4==4.3.2
Requires-Dist: mutagen==1.47.0
Requires-Dist: pycparser==2.21
Requires-Dist: pycryptodomex==3.18.0
Requires-Dist: pytermor==2.111.0.dev0
Requires-Dist: requests==2.31.0
Requires-Dist: secretstorage==3.3.3
Requires-Dist: soupsieve==2.5
Requires-Dist: urllib3==2.0.4
Requires-Dist: websockets==11.0.3
Requires-Dist: yt-dlp==2023.7.6
